matplotobjlib/__init__.py
matplotobjlib/colormesh.py
matplotobjlib/curve_fit.py
matplotobjlib/draw.py
matplotobjlib/graph.py
matplotobjlib/histogram.py
matplotobjlib/line.py
matplotobjlib/plotable.py
matplotobjlib/subplot.py
matplotobjlib/type_hints.py
matplotobjlib/utilities.py
matplotobjlib-1.0.1.dist-info/METADATA
matplotobjlib-1.0.1.dist-info/WHEEL
matplotobjlib-1.0.1.dist-info/license.txt
matplotobjlib-1.0.1.dist-info/top_level.txt
matplotobjlib-1.0.1.dist-info/RECORD
