Metadata-Version: 2.1
Name: matplotobjlib
Version: 1.0.1
Summary: Declarative, objected-oriented interface to matplotlib
Home-page: https://github.com/larashores
Author: Lara Shores
Author-email: lara.shores@outlook.com
License: UNKNOWN
Platform: UNKNOWN
Classifier: Intended Audience :: Science/Research
Classifier: License :: OSI Approved :: MIT License
Classifier: Programming Language :: Python :: 3
Classifier: Topic :: Scientific/Engineering
Requires-Python: >=3.4
Requires-Dist: matplotlib
Requires-Dist: pycertainties (==1.*,>=1.0.2)
Requires-Dist: sympy
Requires-Dist: scipy
